<stix:STIX_Package
	xmlns:xsi="http://www.w3.org/2001/XMLSchema-instance"
	xmlns:stix="http://stix.mitre.org/stix-1"
	xmlns:stixCommon="http://stix.mitre.org/common-1"
	xmlns:indicator="http://stix.mitre.org/Indicator-2"
    xmlns:campaign="http://stix.mitre.org/Campaign-1"
	xmlns:ttp="http://stix.mitre.org/TTP-1"
	xmlns:stixVocabs="http://stix.mitre.org/default_vocabularies-1"
	xmlns:cybox="http://cybox.mitre.org/cybox-2"
	xmlns:cyboxCommon="http://cybox.mitre.org/common-2"
	xmlns:cyboxVocabs="http://cybox.mitre.org/default_vocabularies-2"
	xmlns:DomainNameObj="http://cybox.mitre.org/objects#DomainNameObject-1"
	xmlns:marking="http://data-marking.mitre.org/Marking-1"
	xmlns:example="http://example.com/"
	id="example:Indicator-ba1d406e-937c-414f-9231-6e1dbe64fe8b" version="1.2" timestamp="2014-05-08T09:00:00.000000Z">
	<stix:STIX_Header>
		<stix:Title>STIX Validator Example</stix:Title>
		<stix:Package_Intent xsi:type="stixVocabs:PackageIntentVocab-1.0">Indicators</stix:Package_Intent>
		<stix:Description>
			This example document is invalid against the STIX Suggested Practices.

			STIX Suggested Practices state that Indicators should have a Title, Valid_Time_Position, Indicated_TTP and Confidence. The
			only Indicator in this document is missing all of these properties except the Title.
		</stix:Description>
		<stix:Handling>
			<marking:Marking>
				<marking:Controlled_Structure>This is not XPath</marking:Controlled_Structure>
			</marking:Marking>
		</stix:Handling>
	</stix:STIX_Header>
	<stix:Observables cybox_major_version="2" cybox_minor_version="1">
		<cybox:Observable id="example:Observable-12c760ba-cd2c-4f5d-a37d-18212eac7929">
			<cybox:Object>
				<cybox:Properties xsi:type="DomainNameObj:DomainNameObjectType" type="FQDN">
					<cyboxCommon:Custom_Properties>
						<cyboxCommon:Property name="test">No condition attribute!</cyboxCommon:Property>
					</cyboxCommon:Custom_Properties>
					<DomainNameObj:Value apply_condition="ANY">malicious1.example.com##comma##malicious2.example.com##comma##malicious3.example.com</DomainNameObj:Value>
				</cybox:Properties>
				<cybox:Related_Objects>
					<cybox:Related_Object idref="example:Object-12c760ba-cd2c-4f5d-a37d-18212eac7a39">
						<!-- This should pass the idref-with-content checks, since it is a CybOX Related Object -->
						<cybox:Relationship xsi:type="cyboxVocabs:ObjectRelationshipVocab-1.1">Allocated_By</cybox:Relationship>
					</cybox:Related_Object>
				</cybox:Related_Objects>
			</cybox:Object>
		</cybox:Observable>
	</stix:Observables>
	<stix:Indicators>
        <stix:Indicator idref="example:this-will-raise-a-best-practice-warning"/>
		<stix:Indicator xsi:type="indicator:IndicatorType" id="example:Indicator-2e20c5b2-56fa-46cd-9662-8f199c69d2c9" timestamp="2014-02-20T09:00:00.000000Z" version="2.1">
			<indicator:Title>Sample Domain Watchlist Indicator</indicator:Title>
			<indicator:Type xsi:type="stixVocabs:IndicatorTypeVocab-1.0">Domain Watchlist</indicator:Type>
			<indicator:Description>Sample domain Indicator for this watchlist</indicator:Description>
			<indicator:Observable id="example:Observable-87c9a5bb-d005-4b3e-8081-99f720fad62b">
				<cybox:Object id="example:Object-12c760ba-cd2c-4f5d-a37d-18212eac7928">
					<cybox:Properties xsi:type="DomainNameObj:DomainNameObjectType" type="FQDN">
						<cyboxCommon:Custom_Properties>
							<cyboxCommon:Property name="test">No condition attribute!</cyboxCommon:Property>
						</cyboxCommon:Custom_Properties>
						<DomainNameObj:Value apply_condition="ANY">malicious1.example.com##comma##malicious2.example.com##comma##malicious3.example.com</DomainNameObj:Value>
					</cybox:Properties>
				</cybox:Object>
			</indicator:Observable>
		</stix:Indicator>
		<stix:Indicator xsi:type="indicator:IndicatorType" id="example:Indicator-2e20c5b2-56fa-46cd-9662-8f199c69d2d0" version="2.1.1">
			<indicator:Title>Sample Domain Watchlist Indicator</indicator:Title>
			<indicator:Type xsi:type="stixVocabs:IndicatorTypeVocab-1.0">Domain Watchlist</indicator:Type>
			<indicator:Description>Sample domain Indicator for this watchlist</indicator:Description>
			<indicator:Observable id="example:Observable-87c9a5bb-d005-4b3e-8081-99f720fad73c">
				<cybox:Object id="example:Object-12c760ba-cd2c-4f5d-a37d-18212eac7a39">
					<cybox:Properties xsi:type="DomainNameObj:DomainNameObjectType" type="FQDN">
						<DomainNameObj:Value condition="Equals" apply_condition="ANY">malicious1.example.com##comma##malicious2.example.com##comma##malicious3.example.com</DomainNameObj:Value>
					</cybox:Properties>
				</cybox:Object>
			</indicator:Observable>
		</stix:Indicator>
		<stix:Indicator xsi:type="indicator:IndicatorType" id="example:Indicator-2e20c5b2-56fa-46cd-9662-8f199c69d2d1" version="2.2">
			<indicator:Description>Testing idref Observable lookup</indicator:Description>
			<indicator:Observable idref="example:Observable-12c760ba-cd2c-4f5d-a37d-18212eac7929"/>
		</stix:Indicator>
		<stix:Indicator xsi:type="indicator:IndicatorType" idref="example:Indicator-2e20c5b2-56fa-46cd-9662-8f199c69d2c9" timestamp="2014-02-20T10:00:00.000000Z" version="2.2"/>
		<stix:Indicator xsi:type="indicator:IndicatorType" idref="example:Indicator-2e20c5b2-56fa-46cd-9662-8f199c69d2c9" version="2.2">
			<indicator:Title>Testing idref with content</indicator:Title>
		</stix:Indicator>
		<stix:Indicator xsi:type="indicator:IndicatorType" idref="example:Indicator-dup-id-no-ts" version="2.2">
			<indicator:Title>Testing ID duplication without a timestamp</indicator:Title>
		</stix:Indicator>
		<stix:Indicator xsi:type="indicator:IndicatorType" idref="example:Indicator-dup-id-no-ts" version="2.2">
			<indicator:Title>Testing ID duplication without a timestamp</indicator:Title>
		</stix:Indicator>
		<stix:Indicator xsi:type="indicator:IndicatorType" id="example:Indicator-dup-id-with-ts" timestamp="2014-02-20T10:00:00.000000Z" version="2.2">
			<indicator:Title>Testing ID duplication with a timestamp</indicator:Title>
		</stix:Indicator>
		<stix:Indicator xsi:type="indicator:IndicatorType" id="example:Indicator-dup-id-with-ts" timestamp="2014-02-20T10:00:00.000000Z" version="2.2">
			<indicator:Title>Testing ID duplication with a timestamp</indicator:Title>
		</stix:Indicator>
		<stix:Indicator xsi:type="indicator:IndicatorType" id="example:Indicator-dup-id-with-tz-equivalent-ts" timestamp="2014-02-20T10:00:00.000000Z" version="2.2">
			<indicator:Title>Testing ID duplication with a TZ equivalent timestamp</indicator:Title>
		</stix:Indicator>
		<stix:Indicator xsi:type="indicator:IndicatorType" id="example:Indicator-dup-id-with-tz-equivalent-ts" timestamp="2014-02-20T11:00:00+01:00" version="2.2">
			<indicator:Title>Testing ID duplication with an TZ equivalent timestamp</indicator:Title>
		</stix:Indicator>
		<stix:Indicator xsi:type="indicator:IndicatorType" idref="example:Indicator-2e20c5b2-56fa-46cd-9662-8f199c69d2c9" version="2.2">
			<!-- Testing if best practice validation says that an XML comment is "content" for idref-with-content checks -->
		</stix:Indicator>
		<stix:Indicator xsi:type="indicator:IndicatorType" id="example:Indicator-2e20c5b2-56fa-46cd-9662-8f199c69d2dd" version="2.2">
			<indicator:Description>Missing ordinality</indicator:Description>
			<indicator:Description>Missing ordinality</indicator:Description>
			<indicator:Description ordinality='1'>Duplicate ordinality</indicator:Description>
			<indicator:Description ordinality='1'>Duplicate ordinality</indicator:Description>
		</stix:Indicator>
	</stix:Indicators>
    <stix:Campaigns>
        <stix:Campaign xsi:type="campaign:CampaignType" version="1.2">
            <campaign:Title>Testing for Related_Indicators deprecation detection.</campaign:Title>
            <campaign:Related_Indicators>
                <campaign:Related_Indicator>
                    <stixCommon:Indicator idref="example:Indicator-2e20c5b2-56fa-46cd-9662-8f199c69d2d0"/>
                </campaign:Related_Indicator>
            </campaign:Related_Indicators>
        </stix:Campaign>
    </stix:Campaigns>
</stix:STIX_Package>
